rq_retry_scheduler/__init__.py
rq_retry_scheduler/queue.py
rq_retry_scheduler/scheduler.py
rq_retry_scheduler/util.py
rq_retry_scheduler/worker.py
rq_retry_scheduler/cli/__init__.py
rq_retry_scheduler/cli/scheduler.py
rq_retry_scheduler-0.2.1.dist-info/LICENSE
rq_retry_scheduler-0.2.1.dist-info/METADATA
rq_retry_scheduler-0.2.1.dist-info/WHEEL
rq_retry_scheduler-0.2.1.dist-info/entry_points.txt
rq_retry_scheduler-0.2.1.dist-info/top_level.txt
rq_retry_scheduler-0.2.1.dist-info/RECORD
