Metadata-Version: 2.1
Name: rq-retry-scheduler
Version: 0.2.1
Summary: RQ Retry and Scheduler
Home-page: https://github.com/mikemill/rq_retry_scheduler
Author: Michael Miller
Author-email: mikemill@gmail.com
License: MIT
Platform: any
Classifier: Development Status :: 4 - Beta
Classifier: License :: OSI Approved :: MIT License
Classifier: Programming Language :: Python :: 2.7
Classifier: Programming Language :: Python :: 3.4
Classifier: Programming Language :: Python :: 3.5
Classifier: Programming Language :: Python :: 3.6
Requires-Dist: rq (>=0.13)
